{
    "openapi": "3.0.0",
    "info": {
        "title": "Farmácia Pai e Filha API",
        "description": "API para gerenciamento da Farmácia Pai e Filha",
        "version": "1.0.0"
    },
    "paths": {
        "/": {
            "servers": [
                {
                    "url": "http://localhost:8000",
                    "description": "Servidor Local"
                }
            ]
        },
        "/login/auth": {
            "get": {
                "tags": [
                    "Autenticação"
                ],
                "summary": "Exibe o formulário de login",
                "operationId": "6eb587d0dcfdcb28c0e0b772f28a1737",
                "responses": {
                    "200": {
                        "description": "OK"
                    }
                }
            },
            "post": {
                "tags": [
                    "Autenticação"
                ],
                "summary": "Realiza a autenticação",
                "operationId": "e5ac035140b836a2d55659ee0d58df0d",
                "responses": {
                    "302": {
                        "description": "Redirecionamento"
                    }
                }
            }
        },
        "/user/dashboard": {
            "get": {
                "tags": [
                    "Painel"
                ],
                "summary": "Exibe o Dashboard",
                "operationId": "ad585d7d693d6694b71c6084a6277f53",
                "responses": {
                    "200": {
                        "description": "Dados do Dashboard carregados",
                        "content": {
                            "application/json": {
                                "schema": {
                                    "$ref": "#/components/schemas/User"
                                }
                            }
                        }
                    }
                }
            }
        },
        "/logout": {
            "post": {
                "tags": [
                    "Autenticação"
                ],
                "summary": "Encerra a sessão do usuário e invalida o token",
                "operationId": "fe1c1eca634ba2811908fec5e5183950",
                "responses": {
                    "302": {
                        "description": "Logout realizado com sucesso, redireciona para a home"
                    }
                }
            }
        },
        "/employees/{id}": {
            "put": {
                "tags": [
                    "Funcionários"
                ],
                "summary": "Atualiza os dados de um funcionário",
                "operationId": "b3a9ade2ed93de1c1069d0529fee56b0",
                "parameters": [
                    {
                        "name": "id",
                        "in": "path",
                        "description": "ID (UUID) do funcionário",
                        "required": true,
                        "schema": {
                            "type": "string",
                            "format": "uuid"
                        }
                    }
                ],
                "requestBody": {
                    "required": true,
                    "content": {
                        "application/json": {
                            "schema": {
                                "properties": {
                                    "idOccupation": {
                                        "type": "integer",
                                        "example": 1
                                    },
                                    "cpf": {
                                        "type": "string",
                                        "example": "123.456.789-01"
                                    },
                                    "phone": {
                                        "type": "string",
                                        "example": "71988887777"
                                    },
                                    "salary": {
                                        "type": "number",
                                        "format": "float",
                                        "example": 2500.5
                                    },
                                    "isActive": {
                                        "type": "boolean",
                                        "example": true
                                    },
                                    "hire_date": {
                                        "type": "string",
                                        "format": "date"
                                    }
                                },
                                "type": "object"
                            }
                        }
                    }
                },
                "responses": {
                    "200": {
                        "description": "Atualizado com sucesso"
                    },
                    "404": {
                        "description": "Funcionário não encontrado"
                    }
                }
            }
        },
        "/employees/{id}/deactivate": {
            "patch": {
                "tags": [
                    "Funcionários"
                ],
                "summary": "Ativa ou desativa um funcionário (Toggle status)",
                "description": "Inverte o status atual do funcionário.",
                "operationId": "cd7492295a899ffd162e7f791f7d85d0",
                "parameters": [
                    {
                        "name": "id",
                        "in": "path",
                        "description": "ID (UUID) do funcionário",
                        "required": true,
                        "schema": {
                            "type": "string",
                            "format": "uuid"
                        }
                    }
                ],
                "responses": {
                    "200": {
                        "description": "Status alterado com sucesso"
                    },
                    "404": {
                        "description": "Funcionário não encontrado"
                    },
                    "500": {
                        "description": "Erro interno"
                    }
                }
            }
        },
        "/employee/create": {
            "get": {
                "tags": [
                    "Funcionários"
                ],
                "summary": "Exibe o formulário de cadastro de funcionários",
                "operationId": "8e3de8c1d40b4bdca5bfcd3927ffb0c1",
                "responses": {
                    "200": {
                        "description": "Retorna a View HTML"
                    }
                }
            }
        },
        "/employee/store": {
            "post": {
                "tags": [
                    "Funcionários"
                ],
                "summary": "Cadastra um novo funcionário completo",
                "description": "Cria User (Role 2), Employee e Address em uma transação única.",
                "operationId": "c81489ea4475afcd4ca5aea00e9f24af",
                "requestBody": {
                    "required": true,
                    "content": {
                        "application/json": {
                            "schema": {
                                "required": [
                                    "name",
                                    "email",
                                    "password",
                                    "cpf",
                                    "idOccupation"
                                ],
                                "properties": {
                                    "name": {
                                        "type": "string",
                                        "example": "João Silva"
                                    },
                                    "email": {
                                        "type": "string",
                                        "format": "email",
                                        "example": "joao@farmacia.com"
                                    },
                                    "password": {
                                        "type": "string",
                                        "format": "password"
                                    },
                                    "idOccupation": {
                                        "type": "integer",
                                        "example": 1
                                    },
                                    "cpf": {
                                        "type": "string",
                                        "example": "000.000.000-00"
                                    },
                                    "zip_code": {
                                        "type": "string",
                                        "example": "41000-000"
                                    },
                                    "street": {
                                        "type": "string",
                                        "example": "Rua Exemplo"
                                    },
                                    "number": {
                                        "type": "string",
                                        "example": "123"
                                    }
                                },
                                "type": "object"
                            }
                        }
                    }
                },
                "responses": {
                    "201": {
                        "description": "Criado com sucesso"
                    },
                    "422": {
                        "description": "Erro de validação"
                    }
                }
            }
        },
        "/employee/list": {
            "get": {
                "tags": [
                    "Funcionários"
                ],
                "summary": "Lista todos os funcionários cadastrados",
                "operationId": "95f2c7cffa5b7a44f316ef870e829e56",
                "responses": {
                    "200": {
                        "description": "Retorna a view com a listagem completa"
                    }
                }
            }
        },
        "/product/{id}": {
            "get": {
                "tags": [
                    "Products"
                ],
                "summary": "Exibe os detalhes de um produto específico",
                "operationId": "f2f7fd834f846a9529e8a7b87d474cb7",
                "parameters": [
                    {
                        "name": "id",
                        "in": "path",
                        "required": true,
                        "schema": {
                            "type": "string",
                            "format": "uuid"
                        }
                    }
                ],
                "responses": {
                    "200": {
                        "description": "Retorna a view de detalhes do produto"
                    },
                    "404": {
                        "description": "Produto não encontrado"
                    }
                }
            }
        },
        "/product/all-products": {
            "get": {
                "tags": [
                    "Products"
                ],
                "summary": "Lista todos os produtos com paginação e ordenação",
                "operationId": "0b560a752c43a4ca0ba6c998088c0e03",
                "parameters": [
                    {
                        "name": "per_page",
                        "in": "query",
                        "description": "Quantidade de itens (10, 15, 20, 25, 30)",
                        "required": false,
                        "schema": {
                            "type": "integer",
                            "default": 10
                        }
                    },
                    {
                        "name": "page",
                        "in": "query",
                        "description": "Número da página",
                        "required": false,
                        "schema": {
                            "type": "integer"
                        }
                    }
                ],
                "responses": {
                    "200": {
                        "description": "Retorna a view do estoque de produtos"
                    }
                }
            }
        },
        "/product/create": {
            "get": {
                "tags": [
                    "Products"
                ],
                "summary": "Exibe o formulário de cadastro de novo produto",
                "operationId": "20d1710d4f2b88e930fc325732537ba5",
                "responses": {
                    "200": {
                        "description": "Retorna a view de criação"
                    }
                }
            }
        },
        "/create-product": {
            "post": {
                "tags": [
                    "Products"
                ],
                "summary": "Cria um produto e opcionalmente fornecedor/lote",
                "description": "Registra o produto e, se solicitado, cria o fornecedor com endereço e o primeiro lote.",
                "operationId": "450a0d405226a5c2a1305695ed1bb3b4",
                "requestBody": {
                    "required": true,
                    "content": {
                        "application/json": {
                            "schema": {
                                "required": [
                                    "idCategory",
                                    "name",
                                    "price",
                                    "barcode"
                                ],
                                "properties": {
                                    "idCategory": {
                                        "type": "integer",
                                        "example": 1
                                    },
                                    "name": {
                                        "type": "string",
                                        "example": "Dipirona 500mg"
                                    },
                                    "barcode": {
                                        "type": "string",
                                        "example": "7891234567890"
                                    },
                                    "price": {
                                        "type": "string",
                                        "example": "15,50"
                                    },
                                    "min_stock_alert": {
                                        "type": "integer",
                                        "example": 10
                                    },
                                    "novoFornecedor": {
                                        "type": "boolean",
                                        "example": true
                                    },
                                    "cnpj": {
                                        "type": "string",
                                        "example": "12345678000199"
                                    },
                                    "zip_code": {
                                        "type": "string",
                                        "example": "41000000"
                                    },
                                    "street": {
                                        "type": "string",
                                        "example": "Avenida Sete de Setembro"
                                    },
                                    "number": {
                                        "type": "string",
                                        "example": "100"
                                    },
                                    "neighborhood": {
                                        "type": "string",
                                        "example": "Centro"
                                    },
                                    "city": {
                                        "type": "string",
                                        "example": "Salvador"
                                    },
                                    "state": {
                                        "type": "string",
                                        "example": "BA"
                                    },
                                    "batch_code": {
                                        "type": "string",
                                        "example": "LOT-2026-X"
                                    },
                                    "quantity": {
                                        "type": "integer",
                                        "example": 100
                                    },
                                    "expiration_date": {
                                        "type": "string",
                                        "format": "date",
                                        "example": "2028-12-31"
                                    },
                                    "cost_price": {
                                        "type": "string",
                                        "example": "5,50"
                                    }
                                },
                                "type": "object"
                            }
                        }
                    }
                },
                "responses": {
                    "200": {
                        "description": "Sucesso"
                    },
                    "500": {
                        "description": "Erro Interno"
                    }
                }
            }
        },
        "/product/update/{id}": {
            "put": {
                "tags": [
                    "Products"
                ],
                "summary": "Atualiza produto e lote simultaneamente",
                "operationId": "9b072fa387b78c4661dbe7a637bdbac4",
                "parameters": [
                    {
                        "name": "id",
                        "in": "path",
                        "required": true,
                        "schema": {
                            "type": "string",
                            "format": "uuid"
                        }
                    }
                ],
                "requestBody": {
                    "required": true,
                    "content": {
                        "multipart/form-data": {
                            "schema": {
                                "properties": {
                                    "name": {
                                        "type": "string"
                                    },
                                    "idCategory": {
                                        "type": "integer"
                                    },
                                    "price": {
                                        "type": "string"
                                    },
                                    "image_product": {
                                        "type": "string",
                                        "format": "binary"
                                    },
                                    "quantity_now": {
                                        "type": "integer"
                                    },
                                    "idBatch": {
                                        "type": "string",
                                        "format": "uuid"
                                    }
                                },
                                "type": "object"
                            }
                        }
                    }
                },
                "responses": {
                    "200": {
                        "description": "Produto atualizado com sucesso"
                    },
                    "404": {
                        "description": "Produto não encontrado"
                    }
                }
            }
        },
        "/product/deactivate/{id}": {
            "patch": {
                "tags": [
                    "Products"
                ],
                "summary": "Inativa ou reativa um produto (Soft Delete)",
                "operationId": "aedfd8ea60fa0c4118ac7be1faa89ce6",
                "parameters": [
                    {
                        "name": "id",
                        "in": "path",
                        "required": true,
                        "schema": {
                            "type": "string",
                            "format": "uuid"
                        }
                    }
                ],
                "responses": {
                    "200": {
                        "description": "Status alterado com sucesso"
                    },
                    "404": {
                        "description": "Produto não encontrado"
                    }
                }
            }
        },
        "/supplier/supplier-form": {
            "get": {
                "tags": [
                    "Fornecedores"
                ],
                "summary": "Exibe o formulário de cadastro de fornecedores",
                "operationId": "2275dac2803e7245bc51ee05538baef7",
                "responses": {
                    "200": {
                        "description": "Visualização carregada"
                    }
                }
            }
        },
        "/suppliers/list": {
            "get": {
                "tags": [
                    "Fornecedores"
                ],
                "summary": "Lista todos os fornecedores cadastrados",
                "operationId": "c665580028c95d11fca65d7d8ad83f17",
                "responses": {
                    "200": {
                        "description": "Lista carregada com sucesso"
                    }
                }
            }
        },
        "/supplier/store-supplier": {
            "post": {
                "tags": [
                    "Fornecedores"
                ],
                "summary": "Cadastra um fornecedor e seu endereço",
                "operationId": "b56476ae9df3f4d3581ed612fb4051a5",
                "responses": {
                    "201": {
                        "description": "Fornecedor criado com sucesso"
                    }
                }
            }
        },
        "/supplier/update/{id}": {
            "put": {
                "tags": [
                    "Fornecedores"
                ],
                "summary": "Atualiza dados cadastrais e endereço do fornecedor",
                "operationId": "fc99c2deb804f3f5fb3620ef9bb9ed67",
                "parameters": [
                    {
                        "name": "id",
                        "in": "path",
                        "required": true,
                        "schema": {
                            "type": "integer"
                        }
                    }
                ],
                "responses": {
                    "200": {
                        "description": "Dados atualizados com sucesso"
                    }
                }
            }
        },
        "/supplier/deactivate/{id}": {
            "patch": {
                "tags": [
                    "Fornecedores"
                ],
                "summary": "Inativa ou reativa um fornecedor (Soft Delete)",
                "operationId": "3b1be5a8587f7c995ed13e2f6204adc8",
                "parameters": [
                    {
                        "name": "id",
                        "in": "path",
                        "required": true,
                        "schema": {
                            "type": "integer"
                        }
                    }
                ],
                "responses": {
                    "200": {
                        "description": "Status alterado com sucesso"
                    }
                }
            }
        },
        "/login/cadastro": {
            "post": {
                "tags": [
                    "Autenticação"
                ],
                "summary": "Registra um novo cliente no sistema",
                "description": "Cria simultaneamente um registro na tabela Users e na tabela Customers dentro de uma transação.",
                "operationId": "a5b5fb365e903d08932a31efefcf5d36",
                "requestBody": {
                    "required": true,
                    "content": {
                        "application/json": {
                            "schema": {
                                "required": [
                                    "name",
                                    "email",
                                    "password",
                                    "password_confirmation",
                                    "cpf",
                                    "phone",
                                    "birth_date"
                                ],
                                "properties": {
                                    "name": {
                                        "type": "string",
                                        "example": "Alisson Rodrigo"
                                    },
                                    "email": {
                                        "type": "string",
                                        "format": "email",
                                        "example": "alisson@email.com"
                                    },
                                    "password": {
                                        "type": "string",
                                        "format": "password",
                                        "example": "12345678"
                                    },
                                    "password_confirmation": {
                                        "type": "string",
                                        "format": "password",
                                        "example": "12345678"
                                    },
                                    "cpf": {
                                        "type": "string",
                                        "example": "123.456.789-00"
                                    },
                                    "phone": {
                                        "type": "string",
                                        "example": "71988887777"
                                    },
                                    "birth_date": {
                                        "type": "string",
                                        "format": "date",
                                        "example": "1998-03-14"
                                    }
                                },
                                "type": "object"
                            }
                        }
                    }
                },
                "responses": {
                    "302": {
                        "description": "Usuário criado e redirecionado para o login"
                    },
                    "422": {
                        "description": "Erro de validação (CPF duplicado, e-mail inválido, etc.)"
                    },
                    "500": {
                        "description": "Erro interno ao processar a transação no banco"
                    }
                }
            }
        },
        "/user/cadastro": {
            "get": {
                "tags": [
                    "Público / Autenticação"
                ],
                "summary": "Exibe a página de cadastro de novos clientes",
                "description": "Retorna a interface HTML do formulário de registro para clientes (IdRoles = 3).",
                "operationId": "showRegistrationForm",
                "responses": {
                    "200": {
                        "description": "Página de cadastro carregada com sucesso.",
                        "content": {
                            "text/html": {}
                        }
                    },
                    "500": {
                        "description": "Erro interno no servidor ao carregar a view."
                    }
                }
            }
        }
    },
    "components": {
        "schemas": {
            "Address": {
                "title": "Endereço",
                "description": "Modelo de representação de endereços para clientes, funcionários ou fornecedores",
                "properties": {
                    "id": {
                        "type": "string",
                        "format": "uuid",
                        "example": "7c9e1234-5678-90ab-cdef-1234567890ab"
                    },
                    "idCustomer": {
                        "description": "ID do Cliente associado",
                        "type": "string",
                        "format": "uuid",
                        "example": "f47ac10b-58cc-4372-a567-0e02b2c3d479",
                        "nullable": true
                    },
                    "idEmployee": {
                        "description": "ID do Funcionário associado",
                        "type": "string",
                        "format": "uuid",
                        "example": null,
                        "nullable": true
                    },
                    "idSupplier": {
                        "description": "ID do Fornecedor associado",
                        "type": "string",
                        "format": "uuid",
                        "example": null,
                        "nullable": true
                    },
                    "zip_code": {
                        "description": "CEP (apenas números devido ao cast do Model)",
                        "type": "string",
                        "example": "41000000"
                    },
                    "street": {
                        "type": "string",
                        "example": "Avenida Sete de Setembro"
                    },
                    "number": {
                        "type": "string",
                        "example": "100"
                    },
                    "complement": {
                        "type": "string",
                        "example": "Apartamento 201",
                        "nullable": true
                    },
                    "neighborhood": {
                        "type": "string",
                        "example": "Centro"
                    },
                    "city": {
                        "type": "string",
                        "example": "Salvador"
                    },
                    "state": {
                        "type": "string",
                        "maxLength": 2,
                        "example": "BA"
                    }
                },
                "type": "object"
            },
            "Batch": {
                "title": "Lote",
                "description": "Representa a entrada física de um produto no estoque, controlando validade e preço de custo",
                "properties": {
                    "id": {
                        "type": "string",
                        "format": "uuid",
                        "example": "7c9e1234-5678-90ab-cdef-1234567890ab"
                    },
                    "idProducts": {
                        "description": "ID do produto vinculado a este lote",
                        "type": "string",
                        "format": "uuid",
                        "example": "550e8400-e29b-41d4-a716-446655440000"
                    },
                    "idSuppliers": {
                        "description": "ID do fornecedor que entregou este lote",
                        "type": "string",
                        "format": "uuid",
                        "example": "f47ac10b-58cc-4372-a567-0e02b2c3d479"
                    },
                    "batch_code": {
                        "description": "Código de identificação do lote (impresso na embalagem)",
                        "type": "string",
                        "example": "LOT-2026-X12"
                    },
                    "manufacturing_date": {
                        "type": "string",
                        "format": "date",
                        "example": "2025-01-20",
                        "nullable": true
                    },
                    "expiration_date": {
                        "description": "Data de validade do lote",
                        "type": "string",
                        "format": "date",
                        "example": "2028-12-31"
                    },
                    "quantity": {
                        "description": "Quantidade total que entrou no estoque",
                        "type": "integer",
                        "example": 100
                    },
                    "quantity_now": {
                        "description": "Quantidade que ainda resta disponível para venda",
                        "type": "integer",
                        "example": 85
                    },
                    "cost_price": {
                        "description": "Preço de custo unitário do item no momento da entrada",
                        "type": "number",
                        "format": "float",
                        "example": 5.5
                    }
                },
                "type": "object"
            },
            "Category": {
                "title": "Categoria de Medicamento",
                "description": "Classes e subclasses terapêuticas",
                "properties": {
                    "id": {
                        "type": "string",
                        "format": "uuid",
                        "example": "7c9e1234-5678-90ab-cdef-1234567890ab"
                    },
                    "class": {
                        "type": "string",
                        "example": "Sistema Nervoso"
                    },
                    "subclass": {
                        "type": "string",
                        "example": "Analgésicos"
                    },
                    "isActive": {
                        "type": "boolean",
                        "example": true
                    }
                },
                "type": "object"
            },
            "Customer": {
                "title": "Cliente/Funcionário",
                "description": "Estrutura de dados para cadastro de pessoas",
                "properties": {
                    "id": {
                        "type": "string",
                        "format": "uuid",
                        "example": "7c9e1234-5678-90ab-cdef-1234567890ab"
                    },
                    "name": {
                        "type": "string",
                        "example": "Maria Souza"
                    },
                    "cpf": {
                        "type": "string",
                        "example": "000.000.000-00"
                    },
                    "phone": {
                        "type": "string",
                        "example": "71999998888"
                    },
                    "email": {
                        "type": "string",
                        "example": "maria@farmacia.com"
                    },
                    "address": {
                        "type": "string",
                        "example": "Rua Principal, 123"
                    }
                },
                "type": "object"
            },
            "Employee": {
                "title": "Funcionário",
                "description": "Modelo de representação detalhada de um funcionário da farmácia",
                "properties": {
                    "id": {
                        "type": "string",
                        "format": "uuid",
                        "example": "7c9e1234-5678-90ab-cdef-1234567890ab"
                    },
                    "idUsers": {
                        "description": "ID do usuário vinculado para login",
                        "type": "string",
                        "format": "uuid",
                        "example": "550e8400-e29b-41d4-a716-446655440000"
                    },
                    "idOccupations": {
                        "description": "ID do cargo/ocupação",
                        "type": "string",
                        "format": "uuid",
                        "example": "f47ac10b-58cc-4372-a567-0e02b2c3d479"
                    },
                    "cpf": {
                        "description": "CPF (apenas números)",
                        "type": "string",
                        "example": "12345678901"
                    },
                    "rg": {
                        "description": "RG (apenas números)",
                        "type": "string",
                        "example": "123456789"
                    },
                    "phone": {
                        "description": "Telefone com DDD",
                        "type": "string",
                        "example": "71988887777"
                    },
                    "birth_date": {
                        "type": "string",
                        "format": "date",
                        "example": "1998-03-14"
                    },
                    "gender": {
                        "description": "Gênero (M, F, Outro)",
                        "type": "string",
                        "example": "M"
                    },
                    "salary": {
                        "type": "number",
                        "format": "float",
                        "example": 3500.5
                    },
                    "hire_date": {
                        "type": "string",
                        "format": "date",
                        "example": "2026-01-02"
                    },
                    "resignation_date": {
                        "type": "string",
                        "format": "date",
                        "example": null,
                        "nullable": true
                    },
                    "pis": {
                        "description": "Número do PIS",
                        "type": "string",
                        "example": "12012345678"
                    },
                    "ctps": {
                        "description": "Carteira de Trabalho",
                        "type": "string",
                        "example": "12345670001"
                    },
                    "crf": {
                        "description": "Conselho Regional de Farmácia (obrigatório para farmacêuticos)",
                        "type": "string",
                        "example": "12345/BA",
                        "nullable": true
                    },
                    "isActive": {
                        "type": "boolean",
                        "example": true
                    }
                },
                "type": "object"
            },
            "Occupation": {
                "title": "Ocupação/Cargo",
                "description": "Modelo que define os cargos dentro da farmácia e suas exigências legais",
                "properties": {
                    "id": {
                        "type": "string",
                        "format": "uuid",
                        "example": "f47ac10b-58cc-4372-a567-0e02b2c3d479"
                    },
                    "name": {
                        "description": "Nome do cargo",
                        "type": "string",
                        "example": "Farmacêutico RT"
                    },
                    "requires_crf": {
                        "description": "Indica se o cargo exige registro no Conselho Regional de Farmácia",
                        "type": "boolean",
                        "example": true
                    },
                    "isActive": {
                        "description": "Status do cargo no sistema",
                        "type": "boolean",
                        "example": true
                    }
                },
                "type": "object"
            },
            "Product": {
                "title": "Produto",
                "description": "Modelo de representação de um medicamento ou item de conveniência",
                "properties": {
                    "id": {
                        "type": "string",
                        "format": "uuid",
                        "example": "f47ac10b-58cc-4372-a567-0e02b2c3d479"
                    },
                    "idCategory": {
                        "type": "string",
                        "format": "uuid",
                        "example": "f47ac10b-58cc-4372-a567-0e02b2c3d479"
                    },
                    "name": {
                        "type": "string",
                        "example": "Paracetamol 500mg"
                    },
                    "description": {
                        "type": "string",
                        "example": "Analgésico e antitérmico para dores leves"
                    },
                    "barcode": {
                        "type": "string",
                        "example": "7891234567890"
                    },
                    "active_principle": {
                        "type": "string",
                        "example": "Paracetamol"
                    },
                    "isActive": {
                        "type": "boolean",
                        "example": false
                    },
                    "requires_prescription": {
                        "type": "boolean",
                        "example": false
                    },
                    "price": {
                        "type": "number",
                        "format": "float",
                        "example": 15.5
                    },
                    "min_stock_alert": {
                        "type": "integer",
                        "example": 10
                    }
                },
                "type": "object"
            },
            "Role": {
                "title": "Permissão",
                "properties": {
                    "id": {
                        "type": "string",
                        "format": "uuid",
                        "example": "f47ac10b-58cc-4372-a567-0e02b2c3d479"
                    },
                    "roles": {
                        "type": "string",
                        "example": "employee"
                    }
                },
                "type": "object"
            },
            "Supplier": {
                "title": "Fornecedor",
                "description": "Modelo de representação de fornecedores de medicamentos e insumos",
                "properties": {
                    "id": {
                        "type": "string",
                        "format": "uuid",
                        "example": "3f9e4567-e89b-12d3-a456-426614174000"
                    },
                    "company_name": {
                        "description": "Razão Social da empresa",
                        "type": "string",
                        "example": "Distribuidora de Medicamentos Bahia Ltda"
                    },
                    "trade_name": {
                        "description": "Nome Fantasia",
                        "type": "string",
                        "example": "Dismed Salvador"
                    },
                    "cnpj": {
                        "description": "CNPJ (apenas números)",
                        "type": "string",
                        "example": "12345678000199"
                    },
                    "contact_name": {
                        "description": "Nome da pessoa de contato no fornecedor",
                        "type": "string",
                        "example": "Ricardo Oliveira"
                    },
                    "phone": {
                        "description": "Telefone comercial (apenas números)",
                        "type": "string",
                        "example": "7133445566"
                    },
                    "state_registration": {
                        "description": "Inscrição Estadual",
                        "type": "string",
                        "example": "123456789"
                    },
                    "email": {
                        "type": "string",
                        "format": "email",
                        "example": "contato@dismedsalvador.com.br"
                    },
                    "isActive": {
                        "type": "boolean",
                        "example": true
                    }
                },
                "type": "object"
            },
            "User": {
                "title": "Usuário",
                "description": "Modelo de usuário para autenticação",
                "properties": {
                    "id": {
                        "type": "string",
                        "format": "uuid",
                        "example": "7c9e1234-5678-90ab-cdef-1234567890ab"
                    },
                    "name": {
                        "type": "string",
                        "example": "Administrador"
                    },
                    "email": {
                        "type": "string",
                        "format": "email",
                        "example": "admin@admin.com"
                    },
                    "idRoles": {
                        "description": "ID do cargo",
                        "type": "integer",
                        "example": 1
                    },
                    "isActive": {
                        "type": "boolean",
                        "example": true
                    }
                },
                "type": "object"
            }
        }
    },
    "tags": [
        {
            "name": "Autenticação",
            "description": "Endpoints de acesso"
        },
        {
            "name": "Painel",
            "description": "Painel"
        },
        {
            "name": "Funcionários",
            "description": "Funcionários"
        },
        {
            "name": "Products",
            "description": "Products"
        },
        {
            "name": "Fornecedores",
            "description": "Fornecedores"
        },
        {
            "name": "Público / Autenticação",
            "description": "Público / Autenticação"
        }
    ]
}